marqo/__init__.py
marqo/_httprequests.py
marqo/client.py
marqo/cloud_helpers.py
marqo/config.py
marqo/constants.py
marqo/default_instance_mappings.py
marqo/enums.py
marqo/errors.py
marqo/index.py
marqo/instance_mappings.py
marqo/marqo_cloud_instance_mappings.py
marqo/marqo_logging.py
marqo/utils.py
marqo/version.py
marqo/models/__init__.py
marqo/models/create_index_settings.py
marqo/models/marqo_cloud.py
marqo/models/marqo_index.py
marqo/models/marqo_models.py
marqo/models/search_models.py
marqo-3.18.0.dist-info/LICENSE
marqo-3.18.0.dist-info/METADATA
marqo-3.18.0.dist-info/WHEEL
marqo-3.18.0.dist-info/top_level.txt
marqo-3.18.0.dist-info/RECORD
