Metadata-Version: 2.1
Name: marqo
Version: 3.18.0
Summary: Tensor search for humans
Author: marqo org
Author-email: org@marqo.io
Keywords: search python marqo opensearch tensor neural semantic vector embedding
Classifier: Programming Language :: Python :: 3.8
Classifier: License :: OSI Approved :: Apache Software License
Classifier: Operating System :: OS Independent
Requires-Python: >=3
License-File: LICENSE
Requires-Dist: requests
Requires-Dist: urllib3 >=1.26.0
Requires-Dist: pydantic >=2.0.0
Requires-Dist: packaging
